Workbook

Sheet Assumptions
B2: Item | C2: Value
B3: Monthly Electricity Cost (Estimate) | C3: 300
B4: Invoice Delay (Months) | C4: 1
B5: Start Month | C5: 46023
B6: End Month | C6: 46357

Sheet Utilities Accrual Schedule
C2: 46023 | D2: 46054 | E2: 46082 | F2: 46113 | G2: 46143 | H2: 46174 | I2: 46204 | J2: 46235 | K2: 46266 | L2: 46296 | M2: 46327 | N2: 46357
B3: Electricity Expense (P&L) | C3: =Assumptions!$C$3 -> 300 | D3: =Assumptions!$C$3 -> 300 | E3: =Assumptions!$C$3 -> 300 | F3: =Assumptions!$C$3 -> 300 | G3: =Assumptions!$C$3 -> 300 | H3: =Assumptions!$C$3 -> 300 | I3: =Assumptions!$C$3 -> 300 | J3: =Assumptions!$C$3 -> 300 | ... N3: =Assumptions!$C$3 -> 300
B5: Invoice Paid | C5: 0 | D5: 280 | E5: 340 | F5: =E3 -> 300 | G5: 310 | H5: 285 | I5: 290 | J5: 305 | K5: 330 | L5: =K3 -> 300 | M5: 290 | N5: =M3 -> 300
B7: Adjustment (True-up) | C7: 0 | D7: =D5-C3 -> -20 | E7: =E5-D3 -> 40 | F7: =F5-E3 -> 0 | G7: =G5-F3 -> 10 | H7: =H5-G3 -> -15 | I7: =I5-H3 -> -10 | J7: =J5-I3 -> 5 | K7: =K5-J3 -> 30 | ... N7: =N5-M3 -> 0
B9: Accrual Balance | C9: =C3-C5 -> 300 | D9: =C9+D3-D5 -> 320 | E9: =D9+E3-E5 -> 280 | F9: =E9+F3-F5 -> 280 | G9: =F9+G3-G5 -> 270 | H9: =G9+H3-H5 -> 285 | I9: =H9+I3-I5 -> 295 | J9: =I9+J3-J5 -> 290 | K9: =J9+K3-K5 -> 260 | ... N9: =M9+N3-N5 -> 270

Sheet Monthly P&L
C2: 46023 | D2: 46054 | E2: 46082 | F2: 46113 | G2: 46143 | H2: 46174 | I2: 46204 | J2: 46235 | K2: 46266 | L2: 46296 | M2: 46327 | N2: 46357
B3: Electricity Expense | C3: ='Utilities Accrual Schedule'!C3 -> 300 | D3: ='Utilities Accrual Schedule'!D3+'Utilities Accrual Schedule'!D7 -> 280 | E3: ='Utilities Accrual Schedule'!E3+'Utilities Accrual Schedule'!E7 -> 340 | F3: ='Utilities Accrual Schedule'!F3+'Utilities Accrual Schedule'!F7 -> 300 | G3: ='Utilities Accrual Schedule'!G3+'Utilities Accrual Schedule'!G7 -> 310 | H3: ='Utilities Accrual Schedule'!H3+'Utilities Accrual Schedule'!H7 -> 285 | I3: ='Utilities Accrual Schedule'!I3+'Utilities Accrual Schedule'!I7 -> 290 | J3: ='Utilities Accrual Schedule'!J3+'Utilities Accrual Schedule'!J7 -> 305 | K3: ='Utilities Accrual Schedule'!K3+'Utilities Accrual Schedule'!K7 -> 330 | ... N3: ='Utilities Accrual Schedule'!N3+'Utilities Accrual Schedule'!N7 -> 300
